sp_database_mcp/__init__.py
sp_database_mcp/api_client.py
sp_database_mcp/database.py
sp_database_mcp/models.py
sp_database_mcp/server.py
sp_database_mcp/simple_server.py
sp_database_mcp-0.1.2.dist-info/METADATA
sp_database_mcp-0.1.2.dist-info/WHEEL
sp_database_mcp-0.1.2.dist-info/entry_points.txt
sp_database_mcp-0.1.2.dist-info/licenses/LICENSE
sp_database_mcp-0.1.2.dist-info/RECORD
