Metadata-Version: 2.4
Name: sp-database-mcp
Version: 0.1.2
Summary: A Model Context Protocol server for database schema information
Project-URL: Homepage, https://github.com/alexliu/sp-database-mcp
Project-URL: Repository, https://github.com/alexliu/sp-database-mcp
Project-URL: Issues, https://github.com/alexliu/sp-database-mcp/issues
Project-URL: Documentation, https://github.com/alexliu/sp-database-mcp#readme
Author-email: Alex Liu <drowning524@gmail.com>
License: MIT
License-File: LICENSE
Keywords: database,mcp,model-context-protocol,schema
Classifier: Development Status :: 4 - Beta
Classifier: Intended Audience :: Developers
Classifier: License :: OSI Approved :: MIT License
Classifier: Programming Language :: Python :: 3
Classifier: Programming Language :: Python :: 3.10
Classifier: Programming Language :: Python :: 3.11
Classifier: Programming Language :: Python :: 3.12
Classifier: Topic :: Database
Classifier: Topic :: Software Development :: Libraries :: Python Modules
Requires-Python: >=3.10
Requires-Dist: mcp>=1.4.1
Requires-Dist: requests>=2.31.0
Requires-Dist: sqlalchemy>=2.0.0
Provides-Extra: dev
Requires-Dist: black>=23.0.0; extra == 'dev'
Requires-Dist: pytest-asyncio>=0.21.0; extra == 'dev'
Requires-Dist: pytest>=7.0.0; extra == 'dev'
Requires-Dist: ruff>=0.1.0; extra == 'dev'
Provides-Extra: mysql
Requires-Dist: pymysql>=1.1.0; extra == 'mysql'
Provides-Extra: postgresql
Requires-Dist: psycopg2-binary>=2.9.0; extra == 'postgresql'
